Metadata-Version: 1.1
Name: guardian-azure
Version: 0.34
Summary: Azure Blob Storage interface for Guardian scripts
Home-page: UNKNOWN
Author: Noam Nisenholz
Author-email: noamholz@guardian-optech.com
License: UNKNOWN
Platform: UNKNOWN
Classifier: Programming Language :: Python :: 3.6
